<annotation>
	<folder>mask</folder>
	<filename>maksssksksss221.png</filename>
	<path>C:\Users\mihir\OneDrive\Desktop\mask\maksssksksss221.png</path>
	<source>
		<database>Unknown</database>
	</source>
	<size>
		<width>400</width>
		<height>300</height>
		<depth>3</depth>
	</size>
	<segmented>0</segmented>
	<object>
		<name>face</name>
		<pose>Unspecified</pose>
		<truncated>0</truncated>
		<difficult>0</difficult>
		<bndbox>
			<xmin>22</xmin>
			<ymin>204</ymin>
			<xmax>50</xmax>
			<ymax>239</ymax>
		</bndbox>
	</object>
	<object>
		<name>face</name>
		<pose>Unspecified</pose>
		<truncated>0</truncated>
		<difficult>0</difficult>
		<bndbox>
			<xmin>128</xmin>
			<ymin>182</ymin>
			<xmax>158</xmax>
			<ymax>216</ymax>
		</bndbox>
	</object>
	<object>
		<name>face</name>
		<pose>Unspecified</pose>
		<truncated>0</truncated>
		<difficult>0</difficult>
		<bndbox>
			<xmin>207</xmin>
			<ymin>185</ymin>
			<xmax>234</xmax>
			<ymax>220</ymax>
		</bndbox>
	</object>
	<object>
		<name>face</name>
		<pose>Unspecified</pose>
		<truncated>0</truncated>
		<difficult>0</difficult>
		<bndbox>
			<xmin>353</xmin>
			<ymin>216</ymin>
			<xmax>395</xmax>
			<ymax>247</ymax>
		</bndbox>
	</object>
</annotation>
